{
	"class" : {
		 },
	"instance" : {
		"<" : "JZY 5/26/2019 21:00",
		"<=" : "JZY 5/26/2019 21:00",
		"=" : "JZY 5/27/2019 16:33",
		">" : "JZY 5/26/2019 21:03",
		"description" : "MR 6/27/2019 09:51",
		"description:" : "MR 6/27/2019 09:52",
		"duration" : "JZY 6/27/2019 11:19",
		"hash" : "lw 7/25/2019 09:48",
		"id" : "MR 6/27/2019 09:52",
		"id:" : "MR 6/27/2019 09:52",
		"initialize" : "MR 6/27/2019 10:03",
		"isSynchronized" : "MR 6/27/2019 09:52",
		"isSynchronized:" : "MR 6/27/2019 09:52",
		"printOn:" : "MR 6/27/2019 10:03",
		"renameTo:" : "MR 6/27/2019 10:03",
		"startDateAndTime" : "MR 6/27/2019 09:52",
		"startDateAndTime:" : "MR 6/27/2019 09:52",
		"stopDateAndTime" : "MR 6/27/2019 09:52",
		"stopDateAndTime:" : "MR 6/27/2019 09:52",
		"wid" : "MR 6/27/2019 09:52",
		"wid:" : "MR 6/27/2019 09:53" } }
